sandboxy/__init__.py
sandboxy/config.py
sandboxy/errors.py
sandboxy/logging.py
sandboxy/agents/__init__.py
sandboxy/agents/base.py
sandboxy/agents/llm_prompt.py
sandboxy/agents/loader.py
sandboxy/api/__init__.py
sandboxy/api/app.py
sandboxy/api/routes/__init__.py
sandboxy/api/routes/agents.py
sandboxy/api/routes/local.py
sandboxy/api/routes/tools.py
sandboxy/cli/__init__.py
sandboxy/cli/main.py
sandboxy/cli/type_detector.py
sandboxy/core/__init__.py
sandboxy/core/async_runner.py
sandboxy/core/mdl_parser.py
sandboxy/core/runner.py
sandboxy/core/safe_eval.py
sandboxy/core/state.py
sandboxy/datasets/__init__.py
sandboxy/datasets/loader.py
sandboxy/datasets/runner.py
sandboxy/local/context.py
sandboxy/local/results.py
sandboxy/mcp/__init__.py
sandboxy/mcp/client.py
sandboxy/mcp/wrapper.py
sandboxy/providers/__init__.py
sandboxy/providers/anthropic_provider.py
sandboxy/providers/base.py
sandboxy/providers/http_client.py
sandboxy/providers/openai_provider.py
sandboxy/providers/openrouter.py
sandboxy/providers/registry.py
sandboxy/scenarios/__init__.py
sandboxy/scenarios/comparison.py
sandboxy/scenarios/loader.py
sandboxy/scenarios/runner.py
sandboxy/scenarios/unified.py
sandboxy/session/__init__.py
sandboxy/session/manager.py
sandboxy/tools/__init__.py
sandboxy/tools/base.py
sandboxy/tools/loader.py
sandboxy/tools/yaml_tools.py
sandboxy/ui/__init__.py
sandboxy/ui/dist/index.html
sandboxy/ui/dist/assets/index-CgAkYWrJ.css
sandboxy/ui/dist/assets/index-D4zoGFcr.js
sandboxy/utils/__init__.py
sandboxy/utils/time.py
sandboxy-0.0.3.dist-info/METADATA
sandboxy-0.0.3.dist-info/WHEEL
sandboxy-0.0.3.dist-info/entry_points.txt
sandboxy-0.0.3.dist-info/licenses/LICENSE
sandboxy-0.0.3.dist-info/RECORD
