Metadata-Version: 2.4
Name: sandboxy
Version: 0.0.3
Summary: Open-source agent simulation and benchmarking platform
Project-URL: Homepage, https://github.com/sandboxy-ai/sandboxy
Project-URL: Repository, https://github.com/sandboxy-ai/sandboxy
Author: Sandboxy Team
License-Expression: Apache-2.0
License-File: LICENSE
Keywords: agents,ai,benchmarking,llm,simulation
Classifier: Development Status :: 3 - Alpha
Classifier: Intended Audience :: Developers
Classifier: License :: OSI Approved :: Apache Software License
Classifier: Programming Language :: Python :: 3
Classifier: Programming Language :: Python :: 3.12
Classifier: Programming Language :: Python :: 3.13
Classifier: Topic :: Scientific/Engineering :: Artificial Intelligence
Requires-Python: >=3.12
Requires-Dist: anthropic>=0.18.0
Requires-Dist: click>=8.0
Requires-Dist: fastapi>=0.109.0
Requires-Dist: httpx>=0.27.0
Requires-Dist: mcp>=1.0.0
Requires-Dist: openai>=1.0
Requires-Dist: pydantic-settings>=2.0
Requires-Dist: pydantic>=2.0
Requires-Dist: python-dotenv>=1.0.0
Requires-Dist: pyyaml>=6.0
Requires-Dist: simpleeval>=1.0.0
Requires-Dist: sse-starlette>=1.6.0
Requires-Dist: uvicorn[standard]>=0.27.0
Requires-Dist: websockets>=12.0
Provides-Extra: dev
Requires-Dist: pytest-asyncio>=0.23.0; extra == 'dev'
Requires-Dist: pytest-cov>=4.0; extra == 'dev'
Requires-Dist: pytest-mock>=3.12.0; extra == 'dev'
Requires-Dist: pytest-timeout>=2.2.0; extra == 'dev'
Requires-Dist: pytest-xdist>=3.5.0; extra == 'dev'
Requires-Dist: pytest>=8.0; extra == 'dev'
Requires-Dist: respx>=0.21.0; extra == 'dev'
Requires-Dist: ruff>=0.1; extra == 'dev'
